bonobo_docker/__init__.py
bonobo_docker/__main__.py
bonobo_docker/_api.py
bonobo_docker/_version.py
bonobo_docker/logging.py
bonobo_docker/services.py
bonobo_docker/settings.py
bonobo_docker/utils.py
bonobo_docker/commands/__init__.py
bonobo_docker/commands/runc.py
bonobo_docker/images/Dockerfile
bonobo_docker/images/__init__.py
bonobo_docker/images/entrypoint.sh
bonobo_docker/images/pythonrc.py
bonobo_docker-0.6.0.dist-info/DESCRIPTION.rst
bonobo_docker-0.6.0.dist-info/METADATA
bonobo_docker-0.6.0.dist-info/RECORD
bonobo_docker-0.6.0.dist-info/WHEEL
bonobo_docker-0.6.0.dist-info/entry_points.txt
bonobo_docker-0.6.0.dist-info/metadata.json
bonobo_docker-0.6.0.dist-info/top_level.txt
